pyscada/__init__.py
pyscada/bacnet/__init__.py
pyscada/bacnet/admin.py
pyscada/bacnet/apps.py
pyscada/bacnet/device.py
pyscada/bacnet/models.py
pyscada/bacnet/signals.py
pyscada/bacnet/worker.py
pyscada/bacnet/migrations/0001_initial.py
pyscada/bacnet/migrations/0002_auto_20210930_0917.py
pyscada/bacnet/migrations/0003_auto_20210930_0956.py
pyscada/bacnet/migrations/0004_auto_20210930_1020.py
pyscada/bacnet/migrations/0005_add_device_protocol.py
pyscada/bacnet/migrations/0006_remove_bacnetvariable_bacnet_device.py
pyscada/bacnet/migrations/0007_auto_20211004_0928.py
pyscada/bacnet/migrations/0008_auto_20211004_0932.py
pyscada/bacnet/migrations/0009_auto_20211004_0937.py
pyscada/bacnet/migrations/0010_auto_20211004_0939.py
pyscada/bacnet/migrations/0011_auto_20211116_1329.py
pyscada/bacnet/migrations/0012_auto_20211206_1335.py
pyscada/bacnet/migrations/0013_auto_20211206_1550.py
pyscada/bacnet/migrations/0014_auto_20211206_1612.py
pyscada/bacnet/migrations/0015_auto_20220203_1442.py
pyscada/bacnet/migrations/__init__.py
pyscada_bacnet-0.8.0.dist-info/AUTHORS
pyscada_bacnet-0.8.0.dist-info/LICENSE
pyscada_bacnet-0.8.0.dist-info/METADATA
pyscada_bacnet-0.8.0.dist-info/WHEEL
pyscada_bacnet-0.8.0.dist-info/top_level.txt
pyscada_bacnet-0.8.0.dist-info/RECORD
